xystitch/__init__.py
xystitch/all_stitch.py
xystitch/autooptimizer.py
xystitch/benchmark.py
xystitch/blender.py
xystitch/cleaner.py
xystitch/common_stitch.py
xystitch/config.py
xystitch/control_point.py
xystitch/execute.py
xystitch/fortify_stitch.py
xystitch/geometry.py
xystitch/grid_stitch.py
xystitch/image_coordinate_map.py
xystitch/image_map.py
xystitch/linear_optimizer.py
xystitch/merger.py
xystitch/microscopej.py
xystitch/optimizer.py
xystitch/photometric_optimizer.py
xystitch/pimage.py
xystitch/remapper.py
xystitch/single.py
xystitch/sizer.py
xystitch/spatial_map.py
xystitch/statistics.py
xystitch/temp_file.py
xystitch/tiler.py
xystitch/util.py
xystitch/wander_stitch.py
xystitch/image/__init__.py
xystitch/image/inksvg.py
xystitch/image/liner.py
xystitch/image/soften.py
xystitch/pto/__init__.py
xystitch/pto/comment_line.py
xystitch/pto/control_point_line.py
xystitch/pto/image_line.py
xystitch/pto/line.py
xystitch/pto/mode_line.py
xystitch/pto/optimizer_line.py
xystitch/pto/option_line.py
xystitch/pto/panorama_line.py
xystitch/pto/project.py
xystitch/pto/util.py
xystitch/pto/variable_line.py
xystitch-1.1.0.data/scripts/xy-clean
xystitch-1.1.0.data/scripts/xy-cphugin
xystitch-1.1.0.data/scripts/xy-feature
xystitch-1.1.0.data/scripts/xy-hugin
xystitch-1.1.0.data/scripts/xy-move
xystitch-1.1.0.data/scripts/xy-pto
xystitch-1.1.0.data/scripts/xy-stitch
xystitch-1.1.0.data/scripts/xy-ts
xystitch-1.1.0.dist-info/METADATA
xystitch-1.1.0.dist-info/WHEEL
xystitch-1.1.0.dist-info/top_level.txt
xystitch-1.1.0.dist-info/RECORD
