Metadata-Version: 2.1
Name: xystitch
Version: 1.1.0
Summary: Microscope panorama stitching utilities.
Home-page: https://github.com/JohnDMcMaster/xystitch
Author: John McMaster
Author-email: JohnDMcMaster@gmail.com
License: BSD
Keywords: hugin panotools microscope
Platform: UNKNOWN
Classifier: License :: OSI Approved :: BSD License
